<?xml version="1.0" encoding="utf-8" standalone="yes"?>
<Table TableName="GOODS_EXT">
  <Column ColumnName="GOODS_ID" Visible="True" Enabled="False" X="20" Y="10" W="250" H="29">
    <Lable Visible="True" Enabled="False" W="85" H="21">Value</Lable>
    <DataControl Visible="True" Enabled="False" W="150" H="21">Value</DataControl>
  </Column>
  <Column ColumnName="GOODS_CLASS" Visible="True" Enabled="True" X="320" Y="10" W="250" H="29">
    <Lable Visible="True" Enabled="True" W="85" H="21">Value</Lable>
    <DataControl Visible="True" Enabled="True" W="150" H="21">Value</DataControl>
  </Column>
  <Column ColumnName="COMPATIBILITY" Visible="True" Enabled="True" X="620" Y="10" W="250" H="29">
    <Lable Visible="True" Enabled="True" W="85" H="21">Value</Lable>
    <DataControl Visible="True" Enabled="True" W="150" H="21">Value</DataControl>
  </Column>
  <Column ColumnName="UNIT_OF_MASTER" Visible="True" Enabled="True" X="20" Y="45" W="250" H="29">
    <Lable Visible="True" Enabled="True" W="85" H="21">Value</Lable>
    <DataControl Visible="True" Enabled="True" W="150" H="21">Value</DataControl>
  </Column>
  <Column ColumnName="CASE" Visible="True" Enabled="True" X="320" Y="45" W="250" H="29">
    <Lable Visible="True" Enabled="True" W="85" H="21">Value</Lable>
    <DataControl Visible="True" Enabled="True" W="150" H="21">Value</DataControl>
  </Column>
  <Column ColumnName="INNER_PACK" Visible="True" Enabled="True" X="620" Y="45" W="250" H="29">
    <Lable Visible="True" Enabled="True" W="85" H="21">Value</Lable>
    <DataControl Visible="True" Enabled="True" W="150" H="21">Value</DataControl>
  </Column>
  <Column ColumnName="PICK_UNIT" Visible="True" Enabled="True" X="20" Y="80" W="250" H="29">
    <Lable Visible="True" Enabled="True" W="85" H="21">Value</Lable>
    <DataControl Visible="True" Enabled="True" W="150" H="21">Value</DataControl>
  </Column>
  <Column ColumnName="PICK_CASE" Visible="True" Enabled="True" X="320" Y="80" W="250" H="29">
    <Lable Visible="True" Enabled="True" W="85" H="21">Value</Lable>
    <DataControl Visible="True" Enabled="True" W="150" H="21">Value</DataControl>
  </Column>
  <Column ColumnName="PICK_INNER_PACK" Visible="True" Enabled="True" X="620" Y="80" W="250" H="29">
    <Lable Visible="True" Enabled="True" W="85" H="21">Value</Lable>
    <DataControl Visible="True" Enabled="True" W="150" H="21">Value</DataControl>
  </Column>
  <Column ColumnName="PICK_PALLET" Visible="True" Enabled="True" X="20" Y="115" W="250" H="29">
    <Lable Visible="True" Enabled="True" W="85" H="21">Value</Lable>
    <DataControl Visible="True" Enabled="True" W="150" H="21">Value</DataControl>
  </Column>
  <Column ColumnName="COMMINGLE_BATCH" Visible="True" Enabled="True" X="320" Y="115" W="250" H="29">
    <Lable Visible="True" Enabled="True" W="85" H="21">Value</Lable>
    <DataControl Visible="True" Enabled="True" W="150" H="21">Value</DataControl>
  </Column>
  <Column ColumnName="PICK_OF_COMMINGLE_BATCH" Visible="True" Enabled="True" X="620" Y="115" W="250" H="29">
    <Lable Visible="True" Enabled="True" W="85" H="21">Value</Lable>
    <DataControl Visible="True" Enabled="True" W="150" H="21">Value</DataControl>
  </Column>
  <Column ColumnName="OWNER_ID" Visible="True" Enabled="False" X="20" Y="150" W="250" H="29">
    <Lable Visible="True" Enabled="False" W="85" H="21">Value</Lable>
    <DataControl Visible="True" Enabled="False" W="150" H="21">Value</DataControl>
  </Column>
  <Column ColumnName="ABC_CODE" Visible="True" Enabled="True" X="320" Y="150" W="250" H="29">
    <Lable Visible="True" Enabled="True" W="85" H="21">Value</Lable>
    <DataControl Visible="True" Enabled="True" W="150" H="21">Value</DataControl>
  </Column>
  <Column ColumnName="PROVE_REPORT" Visible="True" Enabled="True" X="620" Y="150" W="250" H="29">
    <Lable Visible="True" Enabled="True" W="85" H="21">Value</Lable>
    <DataControl Visible="True" Enabled="True" W="150" H="21">Value</DataControl>
  </Column>
  <Column ColumnName="CHECK_CYCLE" Visible="True" Enabled="True" X="20" Y="185" W="250" H="29">
    <Lable Visible="True" Enabled="True" W="85" H="21">Value</Lable>
    <DataControl Visible="True" Enabled="True" W="150" H="21">Value</DataControl>
  </Column>
  <Column ColumnName="CREATE_DATE" Visible="True" Enabled="True" X="320" Y="185" W="250" H="29">
    <Lable Visible="True" Enabled="True" W="85" H="21">Value</Lable>
    <DataControl Visible="True" Enabled="True" W="150" H="21">Value</DataControl>
  </Column>
  <Column ColumnName="CREATE_MAN" Visible="True" Enabled="True" X="620" Y="185" W="250" H="29">
    <Lable Visible="True" Enabled="True" W="85" H="21">Value</Lable>
    <DataControl Visible="True" Enabled="True" W="150" H="21">Value</DataControl>
  </Column>
  <Column ColumnName="MODIFY_DATE" Visible="True" Enabled="True" X="20" Y="220" W="250" H="29">
    <Lable Visible="True" Enabled="True" W="85" H="21">Value</Lable>
    <DataControl Visible="True" Enabled="True" W="150" H="21">Value</DataControl>
  </Column>
  <Column ColumnName="MODIFY_MAN" Visible="True" Enabled="True" X="320" Y="220" W="250" H="29">
    <Lable Visible="True" Enabled="True" W="85" H="21">Value</Lable>
    <DataControl Visible="True" Enabled="True" W="150" H="21">Value</DataControl>
  </Column>
  <Column ColumnName="OUT_VALID" Visible="True" Enabled="True" X="620" Y="220" W="250" H="29">
    <Lable Visible="True" Enabled="True" W="85" H="21">Value</Lable>
    <DataControl Visible="True" Enabled="True" W="150" H="21">Value</DataControl>
  </Column>
  <Column ColumnName="ALLOT_FLAG" Visible="True" Enabled="True" X="20" Y="255" W="250" H="29">
    <Lable Visible="True" Enabled="True" W="85" H="21">Value</Lable>
    <DataControl Visible="True" Enabled="True" W="150" H="21">Value</DataControl>
  </Column>
  <Column ColumnName="COMMNOGOODS_FLAG" Visible="True" Enabled="True" X="320" Y="255" W="250" H="29">
    <Lable Visible="True" Enabled="True" W="85" H="21">Value</Lable>
    <DataControl Visible="True" Enabled="True" W="150" H="21">Value</DataControl>
  </Column>
  <Column ColumnName="VOLRATIO" Visible="True" Enabled="True" X="620" Y="255" W="250" H="29">
    <Lable Visible="True" Enabled="True" W="85" H="21">Value</Lable>
    <DataControl Visible="True" Enabled="True" W="150" H="21">Value</DataControl>
  </Column>
  <Column ColumnName="ISDELETED" Visible="True" Enabled="True" X="20" Y="290" W="250" H="29">
    <Lable Visible="True" Enabled="True" W="85" H="21">Value</Lable>
    <DataControl Visible="True" Enabled="True" W="150" H="21">Value</DataControl>
  </Column>
  <Column ColumnName="ORG_ID" Visible="True" Enabled="False" X="320" Y="290" W="250" H="29">
    <Lable Visible="True" Enabled="False" W="85" H="21">Value</Lable>
    <DataControl Visible="True" Enabled="False" W="150" H="21">Value</DataControl>
  </Column>
  <Column ColumnName="CREATE_ORG" Visible="True" Enabled="True" X="620" Y="290" W="250" H="29">
    <Lable Visible="True" Enabled="True" W="85" H="21">Value</Lable>
    <DataControl Visible="True" Enabled="True" W="150" H="21">Value</DataControl>
  </Column>
  <Column ColumnName="CREATE_ORGSEQ" Visible="True" Enabled="True" X="20" Y="325" W="250" H="29">
    <Lable Visible="True" Enabled="True" W="85" H="21">Value</Lable>
    <DataControl Visible="True" Enabled="True" W="150" H="21">Value</DataControl>
  </Column>
  <Column ColumnName="CREATE_ROLE" Visible="True" Enabled="True" X="320" Y="325" W="250" H="29">
    <Lable Visible="True" Enabled="True" W="85" H="21">Value</Lable>
    <DataControl Visible="True" Enabled="True" W="150" H="21">Value</DataControl>
  </Column>
  <Column ColumnName="WEIGHT" Visible="True" Enabled="True" X="620" Y="325" W="250" H="29">
    <Lable Visible="True" Enabled="True" W="85" H="21">Value</Lable>
    <DataControl Visible="True" Enabled="True" W="150" H="21">Value</DataControl>
  </Column>
  <Column ColumnName="WEIGHT_UNIT" Visible="True" Enabled="True" X="20" Y="360" W="250" H="29">
    <Lable Visible="True" Enabled="True" W="85" H="21">Value</Lable>
    <DataControl Visible="True" Enabled="True" W="150" H="21">Value</DataControl>
  </Column>
  <Column ColumnName="VOLUME" Visible="True" Enabled="True" X="320" Y="360" W="550" H="29">
    <Lable Visible="True" Enabled="True" W="85" H="21">Value</Lable>
    <DataControl Visible="True" Enabled="True" W="450" H="21">Value</DataControl>
  </Column>
  <Column ColumnName="CLIENT_BATCHNUMS" Visible="True" Enabled="True" X="21" Y="399" W="848" H="29">
    <Lable Visible="True" Enabled="True" W="85" H="21">Value</Lable>
    <DataControl Visible="True" Enabled="True" W="748" H="21">Value</DataControl>
  </Column>
  <Column ColumnName="PICK_QTY" Visible="True" Enabled="True" X="21" Y="439" W="250" H="29">
    <Lable Visible="True" Enabled="True" W="85" H="21">Value</Lable>
    <DataControl Visible="True" Enabled="True" W="150" H="21">Value</DataControl>
  </Column>
  <Column ColumnName="MAINTAIN_CYCLE" Visible="True" Enabled="True" X="321" Y="438" W="549" H="29">
    <Lable Visible="True" Enabled="True" W="85" H="21">Value</Lable>
    <DataControl Visible="True" Enabled="True" W="449" H="21">Value</DataControl>
  </Column>
</Table>